expanda/__init__.py
expanda/__main__.py
expanda/extension.py
expanda/shuffling.py
expanda/tokenization.py
expanda/utils.py
expanda/ext/__init__.py
expanda/ext/namuwiki.py
expanda/ext/wikipedia.py
Expanda-1.3.1.dist-info/LICENSE
Expanda-1.3.1.dist-info/METADATA
Expanda-1.3.1.dist-info/WHEEL
Expanda-1.3.1.dist-info/entry_points.txt
Expanda-1.3.1.dist-info/top_level.txt
Expanda-1.3.1.dist-info/RECORD
