Metadata-Version: 2.1
Name: Expanda
Version: 1.3.1
Summary: Integrated Corpus-Building Environment
Home-page: https://github.com/affjljoo3581/Expanda
Author: Jungwoo Park
Author-email: affjljoo3581@gmail.com
License: Apache-2.0
Keywords: expanda,corpus,dataset,nlp
Platform: UNKNOWN
Classifier: Environment :: Console
Classifier: Operating System :: OS Independent
Classifier: Programming Language :: Python :: 3
Classifier: Programming Language :: Python :: 3.6
Classifier: Programming Language :: Python :: 3.7
Classifier: Programming Language :: Python :: 3.8
Classifier: Topic :: Scientific/Engineering :: Artificial Intelligence
Requires-Python: >=3.6.0
Requires-Dist: nltk
Requires-Dist: ijson
Requires-Dist: tqdm (>=4.46.0)
Requires-Dist: mwparserfromhell (>=0.5.4)
Requires-Dist: tokenizers (>=0.7.0)
Requires-Dist: kss (==1.3.1)
